drf_batch_requests/__init__.py
drf_batch_requests/exceptions.py
drf_batch_requests/graph.py
drf_batch_requests/request.py
drf_batch_requests/response.py
drf_batch_requests/serializers.py
drf_batch_requests/settings.py
drf_batch_requests/urls.py
drf_batch_requests/utils.py
drf_batch_requests/views.py
drf_batch_requests/__pycache__/__init__.cpython-310.pyc
drf_batch_requests/__pycache__/__init__.cpython-36.pyc
drf_batch_requests/__pycache__/__init__.cpython-37.pyc
drf_batch_requests/__pycache__/__init__.cpython-39.pyc
drf_batch_requests/__pycache__/exceptions.cpython-310.pyc
drf_batch_requests/__pycache__/exceptions.cpython-36.pyc
drf_batch_requests/__pycache__/exceptions.cpython-37.pyc
drf_batch_requests/__pycache__/exceptions.cpython-39.pyc
drf_batch_requests/__pycache__/graph.cpython-310.pyc
drf_batch_requests/__pycache__/graph.cpython-36.pyc
drf_batch_requests/__pycache__/graph.cpython-37.pyc
drf_batch_requests/__pycache__/graph.cpython-39.pyc
drf_batch_requests/__pycache__/request.cpython-310.pyc
drf_batch_requests/__pycache__/request.cpython-36.pyc
drf_batch_requests/__pycache__/request.cpython-37.pyc
drf_batch_requests/__pycache__/request.cpython-39.pyc
drf_batch_requests/__pycache__/response.cpython-310.pyc
drf_batch_requests/__pycache__/response.cpython-36.pyc
drf_batch_requests/__pycache__/response.cpython-37.pyc
drf_batch_requests/__pycache__/response.cpython-39.pyc
drf_batch_requests/__pycache__/serializers.cpython-310.pyc
drf_batch_requests/__pycache__/serializers.cpython-36.pyc
drf_batch_requests/__pycache__/serializers.cpython-37.pyc
drf_batch_requests/__pycache__/serializers.cpython-39.pyc
drf_batch_requests/__pycache__/settings.cpython-310.pyc
drf_batch_requests/__pycache__/settings.cpython-36.pyc
drf_batch_requests/__pycache__/settings.cpython-37.pyc
drf_batch_requests/__pycache__/settings.cpython-39.pyc
drf_batch_requests/__pycache__/urls.cpython-310.pyc
drf_batch_requests/__pycache__/urls.cpython-36.pyc
drf_batch_requests-0.9.5.dist-info/LICENSE
drf_batch_requests-0.9.5.dist-info/METADATA
drf_batch_requests-0.9.5.dist-info/WHEEL
drf_batch_requests-0.9.5.dist-info/top_level.txt
drf_batch_requests-0.9.5.dist-info/zip-safe
drf_batch_requests-0.9.5.dist-info/RECORD
