Metadata-Version: 2.1
Name: drf-batch-requests
Version: 0.9.5
Summary: Facebook-like implementation of batch requests
Home-page: https://github.com/roman-karpovich/drf-batch-requests
Author: Roman Karpovich
Author-email: fpm.th13f@gmail.com
License: MIT License
Keywords: django django-rest-framework drf batch
Classifier: Development Status :: 4 - Beta
Classifier: Environment :: Web Environment
Classifier: Framework :: Django
Classifier: Intended Audience :: Developers
Classifier: License :: OSI Approved :: MIT License
Classifier: Operating System :: OS Independent
Classifier: Programming Language :: Python
Classifier: Programming Language :: Python :: 3
Classifier: Programming Language :: Python :: 3.6
Classifier: Programming Language :: Python :: 3.7
Classifier: Programming Language :: Python :: 3.8
Classifier: Topic :: Internet :: WWW/HTTP
Classifier: Topic :: Internet :: WWW/HTTP :: Dynamic Content
License-File: LICENSE
Requires-Dist: django (>=1.11)
Requires-Dist: djangorestframework
